{
  "a_comp_cor_00": {
    "CumulativeVarianceExplained": 0.1026554635,
    "Mask": "combined",
    "Method": "aCompCor",
    "Retained": true,
    "SingularValue": 121.5879048422,
    "VarianceExplained": 0.1026554635
  },
  "a_comp_cor_01": {
    "CumulativeVarianceExplained": 0.1914877698,
    "Mask": "combined",
    "Method": "aCompCor",
    "Retained": true,
    "SingularValue": 113.1057827888,
    "VarianceExplained": 0.0888323063
  },
  "a_comp_cor_02": {
    "CumulativeVarianceExplained": 0.2518630104,
    "Mask": "combined",
    "Method": "aCompCor",
    "Retained": true,
    "SingularValue": 93.2456923546,
    "VarianceExplained": 0.0603752406
  },
  "a_comp_cor_03": {
    "CumulativeVarianceExplained": 0.2988386805,
    "Mask": "combined",
    "Method": "aCompCor",
    "Retained": true,
    "SingularValue": 82.2499860787,
    "VarianceExplained": 0.0469756702
  },
  "a_comp_cor_04": {
    "CumulativeVarianceExplained": 0.337068446,
    "Mask": "combined",
    "Method": "aCompCor",
    "Retained": true,
    "SingularValue": 74.1993597155,
    "VarianceExplained": 0.0382297655
  },
  "a_comp_cor_05": {
    "CumulativeVarianceExplained": 0.3693625045,
    "Mask": "combined",
    "Method": "aCompCor",
    "Retained": true,
    "SingularValue": 68.1962752541,
    "VarianceExplained": 0.0322940585
  },
  "a_comp_cor_06": {
    "CumulativeVarianceExplained": 0.3959559568,
    "Mask": "combined",
    "Method": "aCompCor",
    "Retained": true,
    "SingularValue": 61.8851860587,
    "VarianceExplained": 0.0265934523
  },
  "a_comp_cor_07": {
    "CumulativeVarianceExplained": 0.4184661838,
    "Mask": "combined",
    "Method": "aCompCor",
    "Retained": true,
    "SingularValue": 56.9363047999,
    "VarianceExplained": 0.022510227
  },
  "a_comp_cor_08": {
    "CumulativeVarianceExplained": 0.4385677233,
    "Mask": "combined",
    "Method": "aCompCor",
    "Retained": true,
    "SingularValue": 53.8039302647,
    "VarianceExplained": 0.0201015395
  },
  "a_comp_cor_09": {
    "CumulativeVarianceExplained": 0.457819878,
    "Mask": "combined",
    "Method": "aCompCor",
    "Retained": true,
    "SingularValue": 52.6549267262,
    "VarianceExplained": 0.0192521547
  },
  "a_comp_cor_10": {
    "CumulativeVarianceExplained": 0.4737566472,
    "Mask": "combined",
    "Method": "aCompCor",
    "Retained": true,
    "SingularValue": 47.9070557953,
    "VarianceExplained": 0.0159367691
  },
  "a_comp_cor_11": {
    "CumulativeVarianceExplained": 0.4882540591,
    "Mask": "combined",
    "Method": "aCompCor",
    "Retained": true,
    "SingularValue": 45.6924642419,
    "VarianceExplained": 0.0144974119
  },
  "a_comp_cor_12": {
    "CumulativeVarianceExplained": 0.5015903908,
    "Mask": "combined",
    "Method": "aCompCor",
    "Retained": true,
    "SingularValue": 43.8245570984,
    "VarianceExplained": 0.0133363317
  },
  "aroma_motion_1": {
    "CSFFraction": 0.01,
    "EdgeFraction": 0.63,
    "HighFrequencyContent": 0.04,
    "MaximumRpCorrelation": 0.89,
    "Method": {
      "Name": "ICA-AROMA",
      "Version": "0.4.5"
    },
    "ModelVarianceExplained": 0.0613248089,
    "MotionNoise": true,
    "TotalVarianceExplained": 0.0527238646
  },
  "aroma_motion_10": {
    "CSFFraction": 0.2,
    "EdgeFraction": 0.65,
    "HighFrequencyContent": 0.3,
    "MaximumRpCorrelation": 0.3,
    "Method": {
      "Name": "ICA-AROMA",
      "Version": "0.4.5"
    },
    "ModelVarianceExplained": 0.0250548331,
    "MotionNoise": true,
    "TotalVarianceExplained": 0.0215408356
  },
  "aroma_motion_11": {
    "CSFFraction": 0.01,
    "EdgeFraction": 0.33,
    "HighFrequencyContent": 0.17,
    "MaximumRpCorrelation": 0.43,
    "Method": {
      "Name": "ICA-AROMA",
      "Version": "0.4.5"
    },
    "ModelVarianceExplained": 0.0245036246,
    "MotionNoise": false,
    "TotalVarianceExplained": 0.0210669353
  },
  "aroma_motion_12": {
    "CSFFraction": 0.01,
    "EdgeFraction": 0.46,
    "HighFrequencyContent": 0.12,
    "MaximumRpCorrelation": 0.4,
    "Method": {
      "Name": "ICA-AROMA",
      "Version": "0.4.5"
    },
    "ModelVarianceExplained": 0.0244769078,
    "MotionNoise": false,
    "TotalVarianceExplained": 0.0210439656
  },
  "aroma_motion_13": {
    "CSFFraction": 0.0,
    "EdgeFraction": 0.35,
    "HighFrequencyContent": 0.2,
    "MaximumRpCorrelation": 0.51,
    "Method": {
      "Name": "ICA-AROMA",
      "Version": "0.4.5"
    },
    "ModelVarianceExplained": 0.0238838345,
    "MotionNoise": false,
    "TotalVarianceExplained": 0.0205340722
  },
  "aroma_motion_14": {
    "CSFFraction": 0.01,
    "EdgeFraction": 0.51,
    "HighFrequencyContent": 0.07,
    "MaximumRpCorrelation": 0.52,
    "Method": {
      "Name": "ICA-AROMA",
      "Version": "0.4.5"
    },
    "ModelVarianceExplained": 0.023820509,
    "MotionNoise": false,
    "TotalVarianceExplained": 0.0204796283
  },
  "aroma_motion_15": {
    "CSFFraction": 0.03,
    "EdgeFraction": 0.48,
    "HighFrequencyContent": 0.35,
    "MaximumRpCorrelation": 0.42,
    "Method": {
      "Name": "ICA-AROMA",
      "Version": "0.4.5"
    },
    "ModelVarianceExplained": 0.0232514126,
    "MotionNoise": false,
    "TotalVarianceExplained": 0.019990349
  },
  "aroma_motion_16": {
    "CSFFraction": 0.12,
    "EdgeFraction": 0.6,
    "HighFrequencyContent": 0.23,
    "MaximumRpCorrelation": 0.37,
    "Method": {
      "Name": "ICA-AROMA",
      "Version": "0.4.5"
    },
    "ModelVarianceExplained": 0.0230700815,
    "MotionNoise": true,
    "TotalVarianceExplained": 0.0198344499
  },
  "aroma_motion_17": {
    "CSFFraction": 0.07,
    "EdgeFraction": 0.24,
    "HighFrequencyContent": 0.36,
    "MaximumRpCorrelation": 0.35,
    "Method": {
      "Name": "ICA-AROMA",
      "Version": "0.4.5"
    },
    "ModelVarianceExplained": 0.0230306181,
    "MotionNoise": true,
    "TotalVarianceExplained": 0.0198005214
  },
  "aroma_motion_18": {
    "CSFFraction": 0.0,
    "EdgeFraction": 0.33,
    "HighFrequencyContent": 0.19,
    "MaximumRpCorrelation": 0.2,
    "Method": {
      "Name": "ICA-AROMA",
      "Version": "0.4.5"
    },
    "ModelVarianceExplained": 0.022961169,
    "MotionNoise": false,
    "TotalVarianceExplained": 0.0197408127
  },
  "aroma_motion_19": {
    "CSFFraction": 0.0,
    "EdgeFraction": 0.66,
    "HighFrequencyContent": 0.19,
    "MaximumRpCorrelation": 0.39,
    "Method": {
      "Name": "ICA-AROMA",
      "Version": "0.4.5"
    },
    "ModelVarianceExplained": 0.0226598154,
    "MotionNoise": true,
    "TotalVarianceExplained": 0.0194817246
  },
  "aroma_motion_2": {
    "CSFFraction": 0.01,
    "EdgeFraction": 0.63,
    "HighFrequencyContent": 0.03,
    "MaximumRpCorrelation": 0.91,
    "Method": {
      "Name": "ICA-AROMA",
      "Version": "0.4.5"
    },
    "ModelVarianceExplained": 0.0405734894,
    "MotionNoise": true,
    "TotalVarianceExplained": 0.034882965
  },
  "aroma_motion_20": {
    "CSFFraction": 0.02,
    "EdgeFraction": 0.66,
    "HighFrequencyContent": 0.17,
    "MaximumRpCorrelation": 0.88,
    "Method": {
      "Name": "ICA-AROMA",
      "Version": "0.4.5"
    },
    "ModelVarianceExplained": 0.0222000633,
    "MotionNoise": true,
    "TotalVarianceExplained": 0.0190864538
  },
  "aroma_motion_21": {
    "CSFFraction": 0.04,
    "EdgeFraction": 0.3,
    "HighFrequencyContent": 0.25,
    "MaximumRpCorrelation": 0.71,
    "Method": {
      "Name": "ICA-AROMA",
      "Version": "0.4.5"
    },
    "ModelVarianceExplained": 0.0219889655,
    "MotionNoise": false,
    "TotalVarianceExplained": 0.0189049629
  },
  "aroma_motion_22": {
    "CSFFraction": 0.03,
    "EdgeFraction": 0.41,
    "HighFrequencyContent": 0.2,
    "MaximumRpCorrelation": 0.27,
    "Method": {
      "Name": "ICA-AROMA",
      "Version": "0.4.5"
    },
    "ModelVarianceExplained": 0.0219460288,
    "MotionNoise": false,
    "TotalVarianceExplained": 0.0188680482
  },
  "aroma_motion_23": {
    "CSFFraction": 0.02,
    "EdgeFraction": 0.36,
    "HighFrequencyContent": 0.36,
    "MaximumRpCorrelation": 0.4,
    "Method": {
      "Name": "ICA-AROMA",
      "Version": "0.4.5"
    },
    "ModelVarianceExplained": 0.0214686279,
    "MotionNoise": true,
    "TotalVarianceExplained": 0.0184576039
  },
  "aroma_motion_24": {
    "CSFFraction": 0.01,
    "EdgeFraction": 0.58,
    "HighFrequencyContent": 0.22,
    "MaximumRpCorrelation": 0.32,
    "Method": {
      "Name": "ICA-AROMA",
      "Version": "0.4.5"
    },
    "ModelVarianceExplained": 0.020681659,
    "MotionNoise": false,
    "TotalVarianceExplained": 0.0177810092
  },
  "aroma_motion_25": {
    "CSFFraction": 0.01,
    "EdgeFraction": 0.39,
    "HighFrequencyContent": 0.17,
    "MaximumRpCorrelation": 0.49,
    "Method": {
      "Name": "ICA-AROMA",
      "Version": "0.4.5"
    },
    "ModelVarianceExplained": 0.0204336571,
    "MotionNoise": false,
    "TotalVarianceExplained": 0.0175677901
  },
  "aroma_motion_26": {
    "CSFFraction": 0.01,
    "EdgeFraction": 0.46,
    "HighFrequencyContent": 0.28,
    "MaximumRpCorrelation": 0.46,
    "Method": {
      "Name": "ICA-AROMA",
      "Version": "0.4.5"
    },
    "ModelVarianceExplained": 0.020216202,
    "MotionNoise": false,
    "TotalVarianceExplained": 0.0173808336
  },
  "aroma_motion_27": {
    "CSFFraction": 0.14,
    "EdgeFraction": 0.5,
    "HighFrequencyContent": 0.36,
    "MaximumRpCorrelation": 0.58,
    "Method": {
      "Name": "ICA-AROMA",
      "Version": "0.4.5"
    },
    "ModelVarianceExplained": 0.0201755925,
    "MotionNoise": true,
    "TotalVarianceExplained": 0.0173459196
  },
  "aroma_motion_28": {
    "CSFFraction": 0.01,
    "EdgeFraction": 0.47,
    "HighFrequencyContent": 0.19,
    "MaximumRpCorrelation": 0.43,
    "Method": {
      "Name": "ICA-AROMA",
      "Version": "0.4.5"
    },
    "ModelVarianceExplained": 0.0196626105,
    "MotionNoise": false,
    "TotalVarianceExplained": 0.0169048846
  },
  "aroma_motion_29": {
    "CSFFraction": 0.06,
    "EdgeFraction": 0.47,
    "HighFrequencyContent": 0.28,
    "MaximumRpCorrelation": 0.59,
    "Method": {
      "Name": "ICA-AROMA",
      "Version": "0.4.5"
    },
    "ModelVarianceExplained": 0.0195684677,
    "MotionNoise": false,
    "TotalVarianceExplained": 0.0168239455
  },
  "aroma_motion_3": {
    "CSFFraction": 0.01,
    "EdgeFraction": 0.47,
    "HighFrequencyContent": 0.09,
    "MaximumRpCorrelation": 0.22,
    "Method": {
      "Name": "ICA-AROMA",
      "Version": "0.4.5"
    },
    "ModelVarianceExplained": 0.0302137804,
    "MotionNoise": false,
    "TotalVarianceExplained": 0.0259762288
  },
  "aroma_motion_30": {
    "CSFFraction": 0.02,
    "EdgeFraction": 0.48,
    "HighFrequencyContent": 0.17,
    "MaximumRpCorrelation": 0.5,
    "Method": {
      "Name": "ICA-AROMA",
      "Version": "0.4.5"
    },
    "ModelVarianceExplained": 0.0194902859,
    "MotionNoise": false,
    "TotalVarianceExplained": 0.0167567288
  },
  "aroma_motion_31": {
    "CSFFraction": 0.06,
    "EdgeFraction": 0.43,
    "HighFrequencyContent": 0.3,
    "MaximumRpCorrelation": 0.58,
    "Method": {
      "Name": "ICA-AROMA",
      "Version": "0.4.5"
    },
    "ModelVarianceExplained": 0.0191108002,
    "MotionNoise": false,
    "TotalVarianceExplained": 0.0164304668
  },
  "aroma_motion_32": {
    "CSFFraction": 0.02,
    "EdgeFraction": 0.26,
    "HighFrequencyContent": 0.3,
    "MaximumRpCorrelation": 0.7,
    "Method": {
      "Name": "ICA-AROMA",
      "Version": "0.4.5"
    },
    "ModelVarianceExplained": 0.0190681529,
    "MotionNoise": false,
    "TotalVarianceExplained": 0.0163938009
  },
  "aroma_motion_33": {
    "CSFFraction": 0.01,
    "EdgeFraction": 0.46,
    "HighFrequencyContent": 0.15,
    "MaximumRpCorrelation": 0.41,
    "Method": {
      "Name": "ICA-AROMA",
      "Version": "0.4.5"
    },
    "ModelVarianceExplained": 0.0186559188,
    "MotionNoise": false,
    "TotalVarianceExplained": 0.0160393836
  },
  "aroma_motion_34": {
    "CSFFraction": 0.05,
    "EdgeFraction": 0.29,
    "HighFrequencyContent": 0.3,
    "MaximumRpCorrelation": 0.41,
    "Method": {
      "Name": "ICA-AROMA",
      "Version": "0.4.5"
    },
    "ModelVarianceExplained": 0.0186098686,
    "MotionNoise": false,
    "TotalVarianceExplained": 0.015999792
  },
  "aroma_motion_35": {
    "CSFFraction": 0.07,
    "EdgeFraction": 0.36,
    "HighFrequencyContent": 0.41,
    "MaximumRpCorrelation": 0.63,
    "Method": {
      "Name": "ICA-AROMA",
      "Version": "0.4.5"
    },
    "ModelVarianceExplained": 0.0182686165,
    "MotionNoise": true,
    "TotalVarianceExplained": 0.0157064014
  },
  "aroma_motion_36": {
    "CSFFraction": 0.01,
    "EdgeFraction": 0.28,
    "HighFrequencyContent": 0.28,
    "MaximumRpCorrelation": 0.67,
    "Method": {
      "Name": "ICA-AROMA",
      "Version": "0.4.5"
    },
    "ModelVarianceExplained": 0.0181080914,
    "MotionNoise": false,
    "TotalVarianceExplained": 0.0155683903
  },
  "aroma_motion_37": {
    "CSFFraction": 0.09,
    "EdgeFraction": 0.41,
    "HighFrequencyContent": 0.31,
    "MaximumRpCorrelation": 0.42,
    "Method": {
      "Name": "ICA-AROMA",
      "Version": "0.4.5"
    },
    "ModelVarianceExplained": 0.0178735956,
    "MotionNoise": false,
    "TotalVarianceExplained": 0.0153667831
  },
  "aroma_motion_38": {
    "CSFFraction": 0.02,
    "EdgeFraction": 0.81,
    "HighFrequencyContent": 0.39,
    "MaximumRpCorrelation": 0.59,
    "Method": {
      "Name": "ICA-AROMA",
      "Version": "0.4.5"
    },
    "ModelVarianceExplained": 0.0172544964,
    "MotionNoise": true,
    "TotalVarianceExplained": 0.014834514
  },
  "aroma_motion_39": {
    "CSFFraction": 0.08,
    "EdgeFraction": 0.8,
    "HighFrequencyContent": 0.3,
    "MaximumRpCorrelation": 0.43,
    "Method": {
      "Name": "ICA-AROMA",
      "Version": "0.4.5"
    },
    "ModelVarianceExplained": 0.0170814935,
    "MotionNoise": true,
    "TotalVarianceExplained": 0.0146857751
  },
  "aroma_motion_4": {
    "CSFFraction": 0.08,
    "EdgeFraction": 0.71,
    "HighFrequencyContent": 0.33,
    "MaximumRpCorrelation": 0.41,
    "Method": {
      "Name": "ICA-AROMA",
      "Version": "0.4.5"
    },
    "ModelVarianceExplained": 0.0284705453,
    "MotionNoise": true,
    "TotalVarianceExplained": 0.0244774864
  },
  "aroma_motion_40": {
    "CSFFraction": 0.11,
    "EdgeFraction": 0.48,
    "HighFrequencyContent": 0.39,
    "MaximumRpCorrelation": 0.36,
    "Method": {
      "Name": "ICA-AROMA",
      "Version": "0.4.5"
    },
    "ModelVarianceExplained": 0.017051293,
    "MotionNoise": true,
    "TotalVarianceExplained": 0.0146598103
  },
  "aroma_motion_41": {
    "CSFFraction": 0.07,
    "EdgeFraction": 0.59,
    "HighFrequencyContent": 0.33,
    "MaximumRpCorrelation": 0.51,
    "Method": {
      "Name": "ICA-AROMA",
      "Version": "0.4.5"
    },
    "ModelVarianceExplained": 0.0165441065,
    "MotionNoise": false,
    "TotalVarianceExplained": 0.0142237579
  },
  "aroma_motion_42": {
    "CSFFraction": 0.15,
    "EdgeFraction": 0.61,
    "HighFrequencyContent": 0.27,
    "MaximumRpCorrelation": 0.3,
    "Method": {
      "Name": "ICA-AROMA",
      "Version": "0.4.5"
    },
    "ModelVarianceExplained": 0.0164714058,
    "MotionNoise": true,
    "TotalVarianceExplained": 0.0141612535
  },
  "aroma_motion_43": {
    "CSFFraction": 0.2,
    "EdgeFraction": 0.65,
    "HighFrequencyContent": 0.54,
    "MaximumRpCorrelation": 0.23,
    "Method": {
      "Name": "ICA-AROMA",
      "Version": "0.4.5"
    },
    "ModelVarianceExplained": 0.0155605366,
    "MotionNoise": true,
    "TotalVarianceExplained": 0.0133781359
  },
  "aroma_motion_44": {
    "CSFFraction": 0.45,
    "EdgeFraction": 0.77,
    "HighFrequencyContent": 0.46,
    "MaximumRpCorrelation": 0.36,
    "Method": {
      "Name": "ICA-AROMA",
      "Version": "0.4.5"
    },
    "ModelVarianceExplained": 0.0155224129,
    "MotionNoise": true,
    "TotalVarianceExplained": 0.0133453591
  },
  "aroma_motion_5": {
    "CSFFraction": 0.1,
    "EdgeFraction": 0.51,
    "HighFrequencyContent": 0.28,
    "MaximumRpCorrelation": 0.32,
    "Method": {
      "Name": "ICA-AROMA",
      "Version": "0.4.5"
    },
    "ModelVarianceExplained": 0.0269629872,
    "MotionNoise": true,
    "TotalVarianceExplained": 0.0231813668
  },
  "aroma_motion_6": {
    "CSFFraction": 0.01,
    "EdgeFraction": 0.34,
    "HighFrequencyContent": 0.15,
    "MaximumRpCorrelation": 0.38,
    "Method": {
      "Name": "ICA-AROMA",
      "Version": "0.4.5"
    },
    "ModelVarianceExplained": 0.0257817852,
    "MotionNoise": false,
    "TotalVarianceExplained": 0.022165831
  },
  "aroma_motion_7": {
    "CSFFraction": 0.0,
    "EdgeFraction": 0.36,
    "HighFrequencyContent": 0.15,
    "MaximumRpCorrelation": 0.43,
    "Method": {
      "Name": "ICA-AROMA",
      "Version": "0.4.5"
    },
    "ModelVarianceExplained": 0.0257470007,
    "MotionNoise": false,
    "TotalVarianceExplained": 0.0221359251
  },
  "aroma_motion_8": {
    "CSFFraction": 0.03,
    "EdgeFraction": 0.56,
    "HighFrequencyContent": 0.38,
    "MaximumRpCorrelation": 0.75,
    "Method": {
      "Name": "ICA-AROMA",
      "Version": "0.4.5"
    },
    "ModelVarianceExplained": 0.0257024753,
    "MotionNoise": true,
    "TotalVarianceExplained": 0.0220976445
  },
  "aroma_motion_9": {
    "CSFFraction": 0.01,
    "EdgeFraction": 0.7,
    "HighFrequencyContent": 0.19,
    "MaximumRpCorrelation": 0.51,
    "Method": {
      "Name": "ICA-AROMA",
      "Version": "0.4.5"
    },
    "ModelVarianceExplained": 0.0254973728,
    "MotionNoise": true,
    "TotalVarianceExplained": 0.0219213081
  },
  "c_comp_cor_00": {
    "CumulativeVarianceExplained": 0.2087991575,
    "Mask": "CSF",
    "Method": "aCompCor",
    "Retained": true,
    "SingularValue": 74.4302307234,
    "VarianceExplained": 0.2087991575
  },
  "c_comp_cor_01": {
    "CumulativeVarianceExplained": 0.3504618845,
    "Mask": "CSF",
    "Method": "aCompCor",
    "Retained": true,
    "SingularValue": 61.3073851489,
    "VarianceExplained": 0.141662727
  },
  "c_comp_cor_02": {
    "CumulativeVarianceExplained": 0.4299046445,
    "Mask": "CSF",
    "Method": "aCompCor",
    "Retained": true,
    "SingularValue": 45.9105141425,
    "VarianceExplained": 0.07944276
  },
  "c_comp_cor_03": {
    "CumulativeVarianceExplained": 0.4879282723,
    "Mask": "CSF",
    "Method": "aCompCor",
    "Retained": true,
    "SingularValue": 39.2362446125,
    "VarianceExplained": 0.0580236277
  },
  "c_comp_cor_04": {
    "CumulativeVarianceExplained": 0.5451003946,
    "Mask": "CSF",
    "Method": "aCompCor",
    "Retained": true,
    "SingularValue": 38.9472816933,
    "VarianceExplained": 0.0571721224
  },
  "csf": {
    "Method": "Mean"
  },
  "csf_wm": {
    "Method": "Mean"
  },
  "global_signal": {
    "Method": "Mean"
  },
  "t_comp_cor_00": {
    "CumulativeVarianceExplained": 0.1774937064,
    "Method": "tCompCor",
    "Retained": true,
    "SingularValue": 102.4512948755,
    "VarianceExplained": 0.1774937064
  },
  "t_comp_cor_01": {
    "CumulativeVarianceExplained": 0.3155954748,
    "Method": "tCompCor",
    "Retained": true,
    "SingularValue": 90.3702726358,
    "VarianceExplained": 0.1381017684
  },
  "t_comp_cor_02": {
    "CumulativeVarianceExplained": 0.4047941131,
    "Method": "tCompCor",
    "Retained": true,
    "SingularValue": 72.6281672051,
    "VarianceExplained": 0.0891986383
  },
  "t_comp_cor_03": {
    "CumulativeVarianceExplained": 0.4756221893,
    "Method": "tCompCor",
    "Retained": true,
    "SingularValue": 64.7185376633,
    "VarianceExplained": 0.0708280763
  },
  "t_comp_cor_04": {
    "CumulativeVarianceExplained": 0.5282533627,
    "Method": "tCompCor",
    "Retained": true,
    "SingularValue": 55.7888615051,
    "VarianceExplained": 0.0526311734
  },
  "tcompcor": {
    "Method": "Mean"
  },
  "w_comp_cor_00": {
    "CumulativeVarianceExplained": 0.1125144314,
    "Mask": "WM",
    "Method": "aCompCor",
    "Retained": true,
    "SingularValue": 80.7464319243,
    "VarianceExplained": 0.1125144314
  },
  "w_comp_cor_01": {
    "CumulativeVarianceExplained": 0.1661549211,
    "Mask": "WM",
    "Method": "aCompCor",
    "Retained": true,
    "SingularValue": 55.752660018,
    "VarianceExplained": 0.0536404897
  },
  "w_comp_cor_02": {
    "CumulativeVarianceExplained": 0.2104545225,
    "Mask": "WM",
    "Method": "aCompCor",
    "Retained": true,
    "SingularValue": 50.666293575,
    "VarianceExplained": 0.0442996014
  },
  "w_comp_cor_03": {
    "CumulativeVarianceExplained": 0.2427703177,
    "Mask": "WM",
    "Method": "aCompCor",
    "Retained": true,
    "SingularValue": 43.2739609476,
    "VarianceExplained": 0.0323157951
  },
  "w_comp_cor_04": {
    "CumulativeVarianceExplained": 0.2704579825,
    "Mask": "WM",
    "Method": "aCompCor",
    "Retained": true,
    "SingularValue": 40.0555214749,
    "VarianceExplained": 0.0276876648
  },
  "w_comp_cor_05": {
    "CumulativeVarianceExplained": 0.2931622244,
    "Mask": "WM",
    "Method": "aCompCor",
    "Retained": true,
    "SingularValue": 36.2721023919,
    "VarianceExplained": 0.0227042419
  },
  "w_comp_cor_06": {
    "CumulativeVarianceExplained": 0.3140674894,
    "Mask": "WM",
    "Method": "aCompCor",
    "Retained": true,
    "SingularValue": 34.8054348602,
    "VarianceExplained": 0.020905265
  },
  "w_comp_cor_07": {
    "CumulativeVarianceExplained": 0.3327956656,
    "Mask": "WM",
    "Method": "aCompCor",
    "Retained": true,
    "SingularValue": 32.9432899857,
    "VarianceExplained": 0.0187281762
  },
  "w_comp_cor_08": {
    "CumulativeVarianceExplained": 0.3512980985,
    "Mask": "WM",
    "Method": "aCompCor",
    "Retained": true,
    "SingularValue": 32.7441442184,
    "VarianceExplained": 0.0185024329
  },
  "w_comp_cor_09": {
    "CumulativeVarianceExplained": 0.3672766726,
    "Mask": "WM",
    "Method": "aCompCor",
    "Retained": true,
    "SingularValue": 30.4290389795,
    "VarianceExplained": 0.0159785741
  },
  "w_comp_cor_10": {
    "CumulativeVarianceExplained": 0.3823997032,
    "Mask": "WM",
    "Method": "aCompCor",
    "Retained": true,
    "SingularValue": 29.6031987708,
    "VarianceExplained": 0.0151230306
  },
  "w_comp_cor_11": {
    "CumulativeVarianceExplained": 0.3962096134,
    "Mask": "WM",
    "Method": "aCompCor",
    "Retained": true,
    "SingularValue": 28.2888082459,
    "VarianceExplained": 0.0138099101
  },
  "w_comp_cor_12": {
    "CumulativeVarianceExplained": 0.4096904895,
    "Mask": "WM",
    "Method": "aCompCor",
    "Retained": true,
    "SingularValue": 27.9497730299,
    "VarianceExplained": 0.0134808762
  },
  "w_comp_cor_13": {
    "CumulativeVarianceExplained": 0.4226141995,
    "Mask": "WM",
    "Method": "aCompCor",
    "Retained": true,
    "SingularValue": 27.366094807,
    "VarianceExplained": 0.01292371
  },
  "w_comp_cor_14": {
    "CumulativeVarianceExplained": 0.4354279864,
    "Mask": "WM",
    "Method": "aCompCor",
    "Retained": true,
    "SingularValue": 27.2494646601,
    "VarianceExplained": 0.0128137869
  },
  "w_comp_cor_15": {
    "CumulativeVarianceExplained": 0.4475767292,
    "Mask": "WM",
    "Method": "aCompCor",
    "Retained": true,
    "SingularValue": 26.5329106012,
    "VarianceExplained": 0.0121487428
  },
  "w_comp_cor_16": {
    "CumulativeVarianceExplained": 0.4591978603,
    "Mask": "WM",
    "Method": "aCompCor",
    "Retained": true,
    "SingularValue": 25.9503624108,
    "VarianceExplained": 0.0116211312
  },
  "w_comp_cor_17": {
    "CumulativeVarianceExplained": 0.4704582918,
    "Mask": "WM",
    "Method": "aCompCor",
    "Retained": true,
    "SingularValue": 25.5444608648,
    "VarianceExplained": 0.0112604314
  },
  "w_comp_cor_18": {
    "CumulativeVarianceExplained": 0.48149136,
    "Mask": "WM",
    "Method": "aCompCor",
    "Retained": true,
    "SingularValue": 25.2852573342,
    "VarianceExplained": 0.0110330682
  },
  "w_comp_cor_19": {
    "CumulativeVarianceExplained": 0.4921263049,
    "Mask": "WM",
    "Method": "aCompCor",
    "Retained": true,
    "SingularValue": 24.824862306,
    "VarianceExplained": 0.0106349449
  },
  "w_comp_cor_20": {
    "CumulativeVarianceExplained": 0.5026983056,
    "Mask": "WM",
    "Method": "aCompCor",
    "Retained": true,
    "SingularValue": 24.7512887515,
    "VarianceExplained": 0.0105720007
  },
  "white_matter": {
    "Method": "Mean"
  }
}