{
  "a_comp_cor_00": {
    "CumulativeVarianceExplained": 0.0959696487,
    "Mask": "combined",
    "Method": "aCompCor",
    "Retained": true,
    "SingularValue": 118.6344845569,
    "VarianceExplained": 0.0959696487
  },
  "a_comp_cor_01": {
    "CumulativeVarianceExplained": 0.1634072317,
    "Mask": "combined",
    "Method": "aCompCor",
    "Retained": true,
    "SingularValue": 99.4477572207,
    "VarianceExplained": 0.067437583
  },
  "a_comp_cor_02": {
    "CumulativeVarianceExplained": 0.2206974575,
    "Mask": "combined",
    "Method": "aCompCor",
    "Retained": true,
    "SingularValue": 91.6609306191,
    "VarianceExplained": 0.0572902259
  },
  "a_comp_cor_03": {
    "CumulativeVarianceExplained": 0.2579277168,
    "Mask": "combined",
    "Method": "aCompCor",
    "Retained": true,
    "SingularValue": 73.8910818752,
    "VarianceExplained": 0.0372302593
  },
  "a_comp_cor_04": {
    "CumulativeVarianceExplained": 0.2911743016,
    "Mask": "combined",
    "Method": "aCompCor",
    "Retained": true,
    "SingularValue": 69.8260563598,
    "VarianceExplained": 0.0332465847
  },
  "a_comp_cor_05": {
    "CumulativeVarianceExplained": 0.3171609007,
    "Mask": "combined",
    "Method": "aCompCor",
    "Retained": true,
    "SingularValue": 61.7331898726,
    "VarianceExplained": 0.0259865991
  },
  "a_comp_cor_06": {
    "CumulativeVarianceExplained": 0.3369318291,
    "Mask": "combined",
    "Method": "aCompCor",
    "Retained": true,
    "SingularValue": 53.8465058813,
    "VarianceExplained": 0.0197709284
  },
  "a_comp_cor_07": {
    "CumulativeVarianceExplained": 0.3541476072,
    "Mask": "combined",
    "Method": "aCompCor",
    "Retained": true,
    "SingularValue": 50.2466744293,
    "VarianceExplained": 0.0172157781
  },
  "a_comp_cor_08": {
    "CumulativeVarianceExplained": 0.370165724,
    "Mask": "combined",
    "Method": "aCompCor",
    "Retained": true,
    "SingularValue": 48.4674000417,
    "VarianceExplained": 0.0160181168
  },
  "a_comp_cor_09": {
    "CumulativeVarianceExplained": 0.3849104829,
    "Mask": "combined",
    "Method": "aCompCor",
    "Retained": true,
    "SingularValue": 46.5010579118,
    "VarianceExplained": 0.0147447589
  },
  "a_comp_cor_10": {
    "CumulativeVarianceExplained": 0.3991305761,
    "Mask": "combined",
    "Method": "aCompCor",
    "Retained": true,
    "SingularValue": 45.6662359734,
    "VarianceExplained": 0.0142200932
  },
  "a_comp_cor_11": {
    "CumulativeVarianceExplained": 0.4130333804,
    "Mask": "combined",
    "Method": "aCompCor",
    "Retained": true,
    "SingularValue": 45.1538930053,
    "VarianceExplained": 0.0139028043
  },
  "a_comp_cor_12": {
    "CumulativeVarianceExplained": 0.4252409907,
    "Mask": "combined",
    "Method": "aCompCor",
    "Retained": true,
    "SingularValue": 42.3115877585,
    "VarianceExplained": 0.0122076103
  },
  "a_comp_cor_13": {
    "CumulativeVarianceExplained": 0.4370138724,
    "Mask": "combined",
    "Method": "aCompCor",
    "Retained": true,
    "SingularValue": 41.5513735975,
    "VarianceExplained": 0.0117728817
  },
  "a_comp_cor_14": {
    "CumulativeVarianceExplained": 0.4486865273,
    "Mask": "combined",
    "Method": "aCompCor",
    "Retained": true,
    "SingularValue": 41.3741246954,
    "VarianceExplained": 0.011672655
  },
  "a_comp_cor_15": {
    "CumulativeVarianceExplained": 0.4600963516,
    "Mask": "combined",
    "Method": "aCompCor",
    "Retained": true,
    "SingularValue": 40.9056665176,
    "VarianceExplained": 0.0114098243
  },
  "a_comp_cor_16": {
    "CumulativeVarianceExplained": 0.470919011,
    "Mask": "combined",
    "Method": "aCompCor",
    "Retained": true,
    "SingularValue": 39.8392348842,
    "VarianceExplained": 0.0108226593
  },
  "a_comp_cor_17": {
    "CumulativeVarianceExplained": 0.4814168475,
    "Mask": "combined",
    "Method": "aCompCor",
    "Retained": true,
    "SingularValue": 39.2368286885,
    "VarianceExplained": 0.0104978365
  },
  "a_comp_cor_18": {
    "CumulativeVarianceExplained": 0.4914071789,
    "Mask": "combined",
    "Method": "aCompCor",
    "Retained": true,
    "SingularValue": 38.2766519108,
    "VarianceExplained": 0.0099903314
  },
  "a_comp_cor_19": {
    "CumulativeVarianceExplained": 0.5013236144,
    "Mask": "combined",
    "Method": "aCompCor",
    "Retained": true,
    "SingularValue": 38.1348279584,
    "VarianceExplained": 0.0099164355
  },
  "aroma_motion_1": {
    "CSFFraction": 0.03,
    "EdgeFraction": 0.53,
    "HighFrequencyContent": 0.15,
    "MaximumRpCorrelation": 0.59,
    "Method": {
      "Name": "ICA-AROMA",
      "Version": "0.4.5"
    },
    "ModelVarianceExplained": 0.0469000073,
    "MotionNoise": false,
    "TotalVarianceExplained": 0.0391733142
  },
  "aroma_motion_10": {
    "CSFFraction": 0.06,
    "EdgeFraction": 0.32,
    "HighFrequencyContent": 0.38,
    "MaximumRpCorrelation": 0.62,
    "Method": {
      "Name": "ICA-AROMA",
      "Version": "0.4.5"
    },
    "ModelVarianceExplained": 0.0297843472,
    "MotionNoise": true,
    "TotalVarianceExplained": 0.0248774288
  },
  "aroma_motion_11": {
    "CSFFraction": 0.01,
    "EdgeFraction": 0.18,
    "HighFrequencyContent": 0.25,
    "MaximumRpCorrelation": 0.55,
    "Method": {
      "Name": "ICA-AROMA",
      "Version": "0.4.5"
    },
    "ModelVarianceExplained": 0.0293528961,
    "MotionNoise": false,
    "TotalVarianceExplained": 0.0245170585
  },
  "aroma_motion_12": {
    "CSFFraction": 0.0,
    "EdgeFraction": 0.33,
    "HighFrequencyContent": 0.14,
    "MaximumRpCorrelation": 0.35,
    "Method": {
      "Name": "ICA-AROMA",
      "Version": "0.4.5"
    },
    "ModelVarianceExplained": 0.0290345933,
    "MotionNoise": false,
    "TotalVarianceExplained": 0.0242511955
  },
  "aroma_motion_13": {
    "CSFFraction": 0.01,
    "EdgeFraction": 0.41,
    "HighFrequencyContent": 0.15,
    "MaximumRpCorrelation": 0.54,
    "Method": {
      "Name": "ICA-AROMA",
      "Version": "0.4.5"
    },
    "ModelVarianceExplained": 0.0286114491,
    "MotionNoise": false,
    "TotalVarianceExplained": 0.0238977636
  },
  "aroma_motion_14": {
    "CSFFraction": 0.13,
    "EdgeFraction": 0.38,
    "HighFrequencyContent": 0.38,
    "MaximumRpCorrelation": 0.38,
    "Method": {
      "Name": "ICA-AROMA",
      "Version": "0.4.5"
    },
    "ModelVarianceExplained": 0.0275965859,
    "MotionNoise": true,
    "TotalVarianceExplained": 0.0230500973
  },
  "aroma_motion_15": {
    "CSFFraction": 0.0,
    "EdgeFraction": 0.59,
    "HighFrequencyContent": 0.11,
    "MaximumRpCorrelation": 0.31,
    "Method": {
      "Name": "ICA-AROMA",
      "Version": "0.4.5"
    },
    "ModelVarianceExplained": 0.0269105362,
    "MotionNoise": false,
    "TotalVarianceExplained": 0.0224770731
  },
  "aroma_motion_16": {
    "CSFFraction": 0.01,
    "EdgeFraction": 0.59,
    "HighFrequencyContent": 0.15,
    "MaximumRpCorrelation": 0.58,
    "Method": {
      "Name": "ICA-AROMA",
      "Version": "0.4.5"
    },
    "ModelVarianceExplained": 0.0268103453,
    "MotionNoise": true,
    "TotalVarianceExplained": 0.0223933885
  },
  "aroma_motion_17": {
    "CSFFraction": 0.0,
    "EdgeFraction": 0.46,
    "HighFrequencyContent": 0.11,
    "MaximumRpCorrelation": 0.23,
    "Method": {
      "Name": "ICA-AROMA",
      "Version": "0.4.5"
    },
    "ModelVarianceExplained": 0.0261287223,
    "MotionNoise": false,
    "TotalVarianceExplained": 0.0218240616
  },
  "aroma_motion_18": {
    "CSFFraction": 0.02,
    "EdgeFraction": 0.48,
    "HighFrequencyContent": 0.7,
    "MaximumRpCorrelation": 0.56,
    "Method": {
      "Name": "ICA-AROMA",
      "Version": "0.4.5"
    },
    "ModelVarianceExplained": 0.025614332,
    "MotionNoise": true,
    "TotalVarianceExplained": 0.0213944162
  },
  "aroma_motion_19": {
    "CSFFraction": 0.05,
    "EdgeFraction": 0.36,
    "HighFrequencyContent": 0.47,
    "MaximumRpCorrelation": 0.36,
    "Method": {
      "Name": "ICA-AROMA",
      "Version": "0.4.5"
    },
    "ModelVarianceExplained": 0.0251512452,
    "MotionNoise": true,
    "TotalVarianceExplained": 0.0210076222
  },
  "aroma_motion_2": {
    "CSFFraction": 0.01,
    "EdgeFraction": 0.45,
    "HighFrequencyContent": 0.17,
    "MaximumRpCorrelation": 0.53,
    "Method": {
      "Name": "ICA-AROMA",
      "Version": "0.4.5"
    },
    "ModelVarianceExplained": 0.0443044321,
    "MotionNoise": false,
    "TotalVarianceExplained": 0.0370053554
  },
  "aroma_motion_20": {
    "CSFFraction": 0.04,
    "EdgeFraction": 0.24,
    "HighFrequencyContent": 0.44,
    "MaximumRpCorrelation": 0.3,
    "Method": {
      "Name": "ICA-AROMA",
      "Version": "0.4.5"
    },
    "ModelVarianceExplained": 0.0251495895,
    "MotionNoise": true,
    "TotalVarianceExplained": 0.0210062392
  },
  "aroma_motion_21": {
    "CSFFraction": 0.02,
    "EdgeFraction": 0.43,
    "HighFrequencyContent": 0.14,
    "MaximumRpCorrelation": 0.52,
    "Method": {
      "Name": "ICA-AROMA",
      "Version": "0.4.5"
    },
    "ModelVarianceExplained": 0.0244786989,
    "MotionNoise": false,
    "TotalVarianceExplained": 0.0204458766
  },
  "aroma_motion_22": {
    "CSFFraction": 0.01,
    "EdgeFraction": 0.28,
    "HighFrequencyContent": 0.28,
    "MaximumRpCorrelation": 0.41,
    "Method": {
      "Name": "ICA-AROMA",
      "Version": "0.4.5"
    },
    "ModelVarianceExplained": 0.02440502,
    "MotionNoise": false,
    "TotalVarianceExplained": 0.0203843362
  },
  "aroma_motion_23": {
    "CSFFraction": 0.04,
    "EdgeFraction": 0.46,
    "HighFrequencyContent": 0.17,
    "MaximumRpCorrelation": 0.37,
    "Method": {
      "Name": "ICA-AROMA",
      "Version": "0.4.5"
    },
    "ModelVarianceExplained": 0.0239018257,
    "MotionNoise": false,
    "TotalVarianceExplained": 0.0199640423
  },
  "aroma_motion_24": {
    "CSFFraction": 0.0,
    "EdgeFraction": 0.4,
    "HighFrequencyContent": 0.12,
    "MaximumRpCorrelation": 0.39,
    "Method": {
      "Name": "ICA-AROMA",
      "Version": "0.4.5"
    },
    "ModelVarianceExplained": 0.0235230613,
    "MotionNoise": false,
    "TotalVarianceExplained": 0.0196476787
  },
  "aroma_motion_25": {
    "CSFFraction": 0.0,
    "EdgeFraction": 0.56,
    "HighFrequencyContent": 0.12,
    "MaximumRpCorrelation": 0.36,
    "Method": {
      "Name": "ICA-AROMA",
      "Version": "0.4.5"
    },
    "ModelVarianceExplained": 0.0228819096,
    "MotionNoise": false,
    "TotalVarianceExplained": 0.0191121555
  },
  "aroma_motion_26": {
    "CSFFraction": 0.0,
    "EdgeFraction": 0.46,
    "HighFrequencyContent": 0.09,
    "MaximumRpCorrelation": 0.41,
    "Method": {
      "Name": "ICA-AROMA",
      "Version": "0.4.5"
    },
    "ModelVarianceExplained": 0.0228400969,
    "MotionNoise": false,
    "TotalVarianceExplained": 0.0190772314
  },
  "aroma_motion_27": {
    "CSFFraction": 0.04,
    "EdgeFraction": 0.61,
    "HighFrequencyContent": 0.57,
    "MaximumRpCorrelation": 0.51,
    "Method": {
      "Name": "ICA-AROMA",
      "Version": "0.4.5"
    },
    "ModelVarianceExplained": 0.0225721243,
    "MotionNoise": true,
    "TotalVarianceExplained": 0.0188534068
  },
  "aroma_motion_28": {
    "CSFFraction": 0.13,
    "EdgeFraction": 0.47,
    "HighFrequencyContent": 0.3,
    "MaximumRpCorrelation": 0.46,
    "Method": {
      "Name": "ICA-AROMA",
      "Version": "0.4.5"
    },
    "ModelVarianceExplained": 0.0224099147,
    "MotionNoise": true,
    "TotalVarianceExplained": 0.018717921
  },
  "aroma_motion_29": {
    "CSFFraction": 0.01,
    "EdgeFraction": 0.36,
    "HighFrequencyContent": 0.23,
    "MaximumRpCorrelation": 0.39,
    "Method": {
      "Name": "ICA-AROMA",
      "Version": "0.4.5"
    },
    "ModelVarianceExplained": 0.022253211,
    "MotionNoise": false,
    "TotalVarianceExplained": 0.0185870339
  },
  "aroma_motion_3": {
    "CSFFraction": 0.02,
    "EdgeFraction": 0.44,
    "HighFrequencyContent": 0.19,
    "MaximumRpCorrelation": 0.53,
    "Method": {
      "Name": "ICA-AROMA",
      "Version": "0.4.5"
    },
    "ModelVarianceExplained": 0.0406912394,
    "MotionNoise": false,
    "TotalVarianceExplained": 0.0339874299
  },
  "aroma_motion_30": {
    "CSFFraction": 0.01,
    "EdgeFraction": 0.82,
    "HighFrequencyContent": 0.71,
    "MaximumRpCorrelation": 0.57,
    "Method": {
      "Name": "ICA-AROMA",
      "Version": "0.4.5"
    },
    "ModelVarianceExplained": 0.022010902,
    "MotionNoise": true,
    "TotalVarianceExplained": 0.0183846449
  },
  "aroma_motion_31": {
    "CSFFraction": 0.02,
    "EdgeFraction": 0.47,
    "HighFrequencyContent": 0.62,
    "MaximumRpCorrelation": 0.59,
    "Method": {
      "Name": "ICA-AROMA",
      "Version": "0.4.5"
    },
    "ModelVarianceExplained": 0.0213360625,
    "MotionNoise": true,
    "TotalVarianceExplained": 0.017820984
  },
  "aroma_motion_32": {
    "CSFFraction": 0.03,
    "EdgeFraction": 0.44,
    "HighFrequencyContent": 0.52,
    "MaximumRpCorrelation": 0.41,
    "Method": {
      "Name": "ICA-AROMA",
      "Version": "0.4.5"
    },
    "ModelVarianceExplained": 0.0208354152,
    "MotionNoise": true,
    "TotalVarianceExplained": 0.0174028175
  },
  "aroma_motion_33": {
    "CSFFraction": 0.01,
    "EdgeFraction": 0.32,
    "HighFrequencyContent": 0.15,
    "MaximumRpCorrelation": 0.32,
    "Method": {
      "Name": "ICA-AROMA",
      "Version": "0.4.5"
    },
    "ModelVarianceExplained": 0.0195215075,
    "MotionNoise": false,
    "TotalVarianceExplained": 0.0163053737
  },
  "aroma_motion_34": {
    "CSFFraction": 0.03,
    "EdgeFraction": 0.3,
    "HighFrequencyContent": 0.11,
    "MaximumRpCorrelation": 0.21,
    "Method": {
      "Name": "ICA-AROMA",
      "Version": "0.4.5"
    },
    "ModelVarianceExplained": 0.0194199546,
    "MotionNoise": false,
    "TotalVarianceExplained": 0.0162205515
  },
  "aroma_motion_35": {
    "CSFFraction": 0.02,
    "EdgeFraction": 0.57,
    "HighFrequencyContent": 0.25,
    "MaximumRpCorrelation": 0.39,
    "Method": {
      "Name": "ICA-AROMA",
      "Version": "0.4.5"
    },
    "ModelVarianceExplained": 0.0193270963,
    "MotionNoise": false,
    "TotalVarianceExplained": 0.0161429914
  },
  "aroma_motion_36": {
    "CSFFraction": 0.01,
    "EdgeFraction": 0.39,
    "HighFrequencyContent": 0.23,
    "MaximumRpCorrelation": 0.26,
    "Method": {
      "Name": "ICA-AROMA",
      "Version": "0.4.5"
    },
    "ModelVarianceExplained": 0.0192579401,
    "MotionNoise": false,
    "TotalVarianceExplained": 0.0160852286
  },
  "aroma_motion_37": {
    "CSFFraction": 0.01,
    "EdgeFraction": 0.48,
    "HighFrequencyContent": 0.46,
    "MaximumRpCorrelation": 0.41,
    "Method": {
      "Name": "ICA-AROMA",
      "Version": "0.4.5"
    },
    "ModelVarianceExplained": 0.0183685023,
    "MotionNoise": true,
    "TotalVarianceExplained": 0.0153423241
  },
  "aroma_motion_4": {
    "CSFFraction": 0.17,
    "EdgeFraction": 0.79,
    "HighFrequencyContent": 0.46,
    "MaximumRpCorrelation": 0.31,
    "Method": {
      "Name": "ICA-AROMA",
      "Version": "0.4.5"
    },
    "ModelVarianceExplained": 0.0369587198,
    "MotionNoise": true,
    "TotalVarianceExplained": 0.0308698362
  },
  "aroma_motion_5": {
    "CSFFraction": 0.05,
    "EdgeFraction": 0.31,
    "HighFrequencyContent": 0.43,
    "MaximumRpCorrelation": 0.32,
    "Method": {
      "Name": "ICA-AROMA",
      "Version": "0.4.5"
    },
    "ModelVarianceExplained": 0.0346911596,
    "MotionNoise": true,
    "TotalVarianceExplained": 0.0289758525
  },
  "aroma_motion_6": {
    "CSFFraction": 0.07,
    "EdgeFraction": 0.2,
    "HighFrequencyContent": 0.27,
    "MaximumRpCorrelation": 0.37,
    "Method": {
      "Name": "ICA-AROMA",
      "Version": "0.4.5"
    },
    "ModelVarianceExplained": 0.0333038924,
    "MotionNoise": false,
    "TotalVarianceExplained": 0.0278171352
  },
  "aroma_motion_7": {
    "CSFFraction": 0.04,
    "EdgeFraction": 0.25,
    "HighFrequencyContent": 0.27,
    "MaximumRpCorrelation": 0.47,
    "Method": {
      "Name": "ICA-AROMA",
      "Version": "0.4.5"
    },
    "ModelVarianceExplained": 0.0319117761,
    "MotionNoise": false,
    "TotalVarianceExplained": 0.0266543676
  },
  "aroma_motion_8": {
    "CSFFraction": 0.17,
    "EdgeFraction": 0.54,
    "HighFrequencyContent": 0.51,
    "MaximumRpCorrelation": 0.31,
    "Method": {
      "Name": "ICA-AROMA",
      "Version": "0.4.5"
    },
    "ModelVarianceExplained": 0.0311529527,
    "MotionNoise": true,
    "TotalVarianceExplained": 0.026020559
  },
  "aroma_motion_9": {
    "CSFFraction": 0.03,
    "EdgeFraction": 0.35,
    "HighFrequencyContent": 0.28,
    "MaximumRpCorrelation": 0.47,
    "Method": {
      "Name": "ICA-AROMA",
      "Version": "0.4.5"
    },
    "ModelVarianceExplained": 0.0305979354,
    "MotionNoise": false,
    "TotalVarianceExplained": 0.0255569798
  },
  "c_comp_cor_00": {
    "CumulativeVarianceExplained": 0.1779651717,
    "Mask": "CSF",
    "Method": "aCompCor",
    "Retained": true,
    "SingularValue": 61.1157346622,
    "VarianceExplained": 0.1779651717
  },
  "c_comp_cor_01": {
    "CumulativeVarianceExplained": 0.303174621,
    "Mask": "CSF",
    "Method": "aCompCor",
    "Retained": true,
    "SingularValue": 51.2630073548,
    "VarianceExplained": 0.1252094494
  },
  "c_comp_cor_02": {
    "CumulativeVarianceExplained": 0.4029658728,
    "Mask": "CSF",
    "Method": "aCompCor",
    "Retained": true,
    "SingularValue": 45.7648204639,
    "VarianceExplained": 0.0997912518
  },
  "c_comp_cor_03": {
    "CumulativeVarianceExplained": 0.4701192777,
    "Mask": "CSF",
    "Method": "aCompCor",
    "Retained": true,
    "SingularValue": 37.5421850931,
    "VarianceExplained": 0.0671534049
  },
  "c_comp_cor_04": {
    "CumulativeVarianceExplained": 0.5194895931,
    "Mask": "CSF",
    "Method": "aCompCor",
    "Retained": true,
    "SingularValue": 32.1898148551,
    "VarianceExplained": 0.0493703154
  },
  "csf": {
    "Method": "Mean"
  },
  "csf_wm": {
    "Method": "Mean"
  },
  "global_signal": {
    "Method": "Mean"
  },
  "t_comp_cor_00": {
    "CumulativeVarianceExplained": 0.3221505263,
    "Method": "tCompCor",
    "Retained": true,
    "SingularValue": 139.8605732686,
    "VarianceExplained": 0.3221505263
  },
  "t_comp_cor_01": {
    "CumulativeVarianceExplained": 0.4693837305,
    "Method": "tCompCor",
    "Retained": true,
    "SingularValue": 94.5515740648,
    "VarianceExplained": 0.1472332042
  },
  "t_comp_cor_02": {
    "CumulativeVarianceExplained": 0.5391332116,
    "Method": "tCompCor",
    "Retained": true,
    "SingularValue": 65.0783258414,
    "VarianceExplained": 0.0697494811
  },
  "tcompcor": {
    "Method": "Mean"
  },
  "w_comp_cor_00": {
    "CumulativeVarianceExplained": 0.095806706,
    "Mask": "WM",
    "Method": "aCompCor",
    "Retained": true,
    "SingularValue": 96.9347125327,
    "VarianceExplained": 0.095806706
  },
  "w_comp_cor_01": {
    "CumulativeVarianceExplained": 0.1551938869,
    "Mask": "WM",
    "Method": "aCompCor",
    "Retained": true,
    "SingularValue": 76.3181312352,
    "VarianceExplained": 0.0593871809
  },
  "w_comp_cor_02": {
    "CumulativeVarianceExplained": 0.2050259396,
    "Mask": "WM",
    "Method": "aCompCor",
    "Retained": true,
    "SingularValue": 69.9094299866,
    "VarianceExplained": 0.0498320527
  },
  "w_comp_cor_03": {
    "CumulativeVarianceExplained": 0.2370805792,
    "Mask": "WM",
    "Method": "aCompCor",
    "Retained": true,
    "SingularValue": 56.0695178992,
    "VarianceExplained": 0.0320546396
  },
  "w_comp_cor_04": {
    "CumulativeVarianceExplained": 0.2678223222,
    "Mask": "WM",
    "Method": "aCompCor",
    "Retained": true,
    "SingularValue": 54.9092632002,
    "VarianceExplained": 0.030741743
  },
  "w_comp_cor_05": {
    "CumulativeVarianceExplained": 0.2922944461,
    "Mask": "WM",
    "Method": "aCompCor",
    "Retained": true,
    "SingularValue": 48.9911014312,
    "VarianceExplained": 0.0244721239
  },
  "w_comp_cor_06": {
    "CumulativeVarianceExplained": 0.311589322,
    "Mask": "WM",
    "Method": "aCompCor",
    "Retained": true,
    "SingularValue": 43.5013132094,
    "VarianceExplained": 0.0192948759
  },
  "w_comp_cor_07": {
    "CumulativeVarianceExplained": 0.3270732147,
    "Mask": "WM",
    "Method": "aCompCor",
    "Retained": true,
    "SingularValue": 38.9691963374,
    "VarianceExplained": 0.0154838927
  },
  "w_comp_cor_08": {
    "CumulativeVarianceExplained": 0.3422598693,
    "Mask": "WM",
    "Method": "aCompCor",
    "Retained": true,
    "SingularValue": 38.593345677,
    "VarianceExplained": 0.0151866545
  },
  "w_comp_cor_09": {
    "CumulativeVarianceExplained": 0.3560950963,
    "Mask": "WM",
    "Method": "aCompCor",
    "Retained": true,
    "SingularValue": 36.8361741401,
    "VarianceExplained": 0.013835227
  },
  "w_comp_cor_10": {
    "CumulativeVarianceExplained": 0.3694284645,
    "Mask": "WM",
    "Method": "aCompCor",
    "Retained": true,
    "SingularValue": 36.1619057263,
    "VarianceExplained": 0.0133333683
  },
  "w_comp_cor_11": {
    "CumulativeVarianceExplained": 0.3825125124,
    "Mask": "WM",
    "Method": "aCompCor",
    "Retained": true,
    "SingularValue": 35.822214808,
    "VarianceExplained": 0.0130840478
  },
  "w_comp_cor_12": {
    "CumulativeVarianceExplained": 0.3945817112,
    "Mask": "WM",
    "Method": "aCompCor",
    "Retained": true,
    "SingularValue": 34.4049233137,
    "VarianceExplained": 0.0120691989
  },
  "w_comp_cor_13": {
    "CumulativeVarianceExplained": 0.4064082853,
    "Mask": "WM",
    "Method": "aCompCor",
    "Retained": true,
    "SingularValue": 34.057349888,
    "VarianceExplained": 0.0118265741
  },
  "w_comp_cor_14": {
    "CumulativeVarianceExplained": 0.4177947012,
    "Mask": "WM",
    "Method": "aCompCor",
    "Retained": true,
    "SingularValue": 33.4175721145,
    "VarianceExplained": 0.0113864159
  },
  "w_comp_cor_15": {
    "CumulativeVarianceExplained": 0.4290141984,
    "Mask": "WM",
    "Method": "aCompCor",
    "Retained": true,
    "SingularValue": 33.1717259429,
    "VarianceExplained": 0.0112194971
  },
  "w_comp_cor_16": {
    "CumulativeVarianceExplained": 0.4396106757,
    "Mask": "WM",
    "Method": "aCompCor",
    "Retained": true,
    "SingularValue": 32.2375574315,
    "VarianceExplained": 0.0105964773
  },
  "w_comp_cor_17": {
    "CumulativeVarianceExplained": 0.4501302384,
    "Mask": "WM",
    "Method": "aCompCor",
    "Retained": true,
    "SingularValue": 32.1203461121,
    "VarianceExplained": 0.0105195627
  },
  "w_comp_cor_18": {
    "CumulativeVarianceExplained": 0.4601843108,
    "Mask": "WM",
    "Method": "aCompCor",
    "Retained": true,
    "SingularValue": 31.4016433915,
    "VarianceExplained": 0.0100540724
  },
  "w_comp_cor_19": {
    "CumulativeVarianceExplained": 0.4699810151,
    "Mask": "WM",
    "Method": "aCompCor",
    "Retained": true,
    "SingularValue": 30.9971219361,
    "VarianceExplained": 0.0097967043
  },
  "w_comp_cor_20": {
    "CumulativeVarianceExplained": 0.4796958256,
    "Mask": "WM",
    "Method": "aCompCor",
    "Retained": true,
    "SingularValue": 30.8672925308,
    "VarianceExplained": 0.0097148104
  },
  "w_comp_cor_21": {
    "CumulativeVarianceExplained": 0.4892774175,
    "Mask": "WM",
    "Method": "aCompCor",
    "Retained": true,
    "SingularValue": 30.6549215204,
    "VarianceExplained": 0.009581592
  },
  "w_comp_cor_22": {
    "CumulativeVarianceExplained": 0.4985501411,
    "Mask": "WM",
    "Method": "aCompCor",
    "Retained": true,
    "SingularValue": 30.1567842774,
    "VarianceExplained": 0.0092727236
  },
  "w_comp_cor_23": {
    "CumulativeVarianceExplained": 0.5076100168,
    "Mask": "WM",
    "Method": "aCompCor",
    "Retained": true,
    "SingularValue": 29.8086626095,
    "VarianceExplained": 0.0090598757
  },
  "white_matter": {
    "Method": "Mean"
  }
}